ua_clarity_api/__init__.py
ua_clarity_api/get_endpoint_map.py
ua_clarity_api/get_multiple_items.xml
ua_clarity_api/post_batch_receive_template.xml
ua_clarity_api/tests/post_container_template.xml
ua_clarity_api/tests/test_ua_clarity_api.py
ua_clarity_api/ua_clarity_api.py
ua_clarity_api-1.1.6.dist-info/LICENSE
ua_clarity_api-1.1.6.dist-info/METADATA
ua_clarity_api-1.1.6.dist-info/WHEEL
ua_clarity_api-1.1.6.dist-info/RECORD
