Metadata-Version: 2.1
Name: ua-clarity-api
Version: 1.1.6
Summary: Provides a simple REST implementation for use with Clarity endpoints.
Author: Your Name
Author-email: you@example.com
Requires-Python: >=3.11,<4.0
Classifier: Programming Language :: Python :: 3
Classifier: Programming Language :: Python :: 3.11
Classifier: Programming Language :: Python :: 3.12
Requires-Dist: beautifulsoup4 (>=4.12.2,<5.0.0)
Requires-Dist: jinja2 (>=3.1.2,<4.0.0)
Requires-Dist: lxml (>=5.1.0,<6.0.0)
Requires-Dist: nose (>=1.3.7,<2.0.0)
Requires-Dist: ua-generic-rest-api (>=2.0.6,<3.0.0)
